amino/__init__.py
amino/acm.py
amino/async_acm.py
amino/async_client.py
amino/async_socket.py
amino/async_sub_client.py
amino/client.py
amino/socket.py
amino/sub_client.py
amino/lib/__init__.py
amino/lib/util/__init__.py
amino/lib/util/device.py
amino/lib/util/exceptions.py
amino/lib/util/headers.py
amino/lib/util/helpers.py
amino/lib/util/objects.py
amino/lib/util/voice_header.py
Amino.py-3.0.10.dist-info/LICENSE
Amino.py-3.0.10.dist-info/METADATA
Amino.py-3.0.10.dist-info/WHEEL
Amino.py-3.0.10.dist-info/top_level.txt
Amino.py-3.0.10.dist-info/RECORD
