Metadata-Version: 2.1
Name: Amino.py
Version: 3.0.10
Summary: A library to create Amino bots.
Home-page: https://github.com/Slimakoi/Amino.py
Download-URL: https://github.com/Slimakoi/Amino.py/tarball/master
Author: Slimakoi
Author-email: slimeytoficial@gmail.com
License: MIT
Keywords: aminoapps,amino-py,amino,amino-bot,narvii,api,python,python3,python3.x,slimakoi,official
License-File: LICENSE
Requires-Dist: setuptools
Requires-Dist: requests
Requires-Dist: six
Requires-Dist: websockets
Requires-Dist: websocket-client (==1.3.1)
Requires-Dist: aiohttp
